pyMobileRobotics/IterativeRobotBase.py
pyMobileRobotics/RobotBase.py
pyMobileRobotics/TimedRobot.py
pyMobileRobotics/Watchdog.py
pyMobileRobotics/__init__.py
pyMobileRobotics/test.py
pyMobileRobotics/test2.py
pyMobileRobotics/test3.py
pyMobileRobotics-0.0.3.dist-info/METADATA
pyMobileRobotics-0.0.3.dist-info/WHEEL
pyMobileRobotics-0.0.3.dist-info/top_level.txt
pyMobileRobotics-0.0.3.dist-info/RECORD
