Metadata-Version: 2.1
Name: pyMobileRobotics
Version: 0.0.3
Summary: WorldSkills Mobile Robotics System
Home-page: https://github.com/CISH-Robotics
Author: CISH Robotics
Author-email: crt@cish.xyz
License: UNKNOWN
Project-URL: Source, https://github.com/CISH-Robotics/pyMobileRobotics
Keywords: robot worldskills mobile robotics
Platform: UNKNOWN
Requires-Python: >=3
Requires-Dist: oclock (>=1.3.0)
Requires-Dist: coloredlogs (>=15.0.1)
Requires-Dist: opencv-contrib-python (>=4.1.0.25)
Requires-Dist: imutils (>=0.5.4)
